setup.py
expectlib/__init__.py
expectlib/__main__.py
expectlib/comparison.py
expectlib/expect.py
expectlib.egg-info/PKG-INFO
expectlib.egg-info/SOURCES.txt
expectlib.egg-info/dependency_links.txt
expectlib.egg-info/requires.txt
expectlib.egg-info/top_level.txt
expectlib/utils/__init__.py
tests/__init__.py
tests/test_comparison.py
tests/test_expect.py