Metadata-Version: 1.2
Name: expectlib
Version: 0.2.0
Summary: An expect style assertion library
Home-page: https://github.com/testingrequired/expect
Author: Kylee Tilley
Author-email: kyleetilley@gmail.com
License: MIT
Platform: UNKNOWN
Requires-Python: >=3.6
